{
	"name" : {
		"text": "Yondu Udonta"
	},

	"icon": {
		"type": "texture",
		"texture": "yondu:textures/icons/yondu_icon.png"
	},
	
	"max_level": 20,
	
	"capsule_color" : 16711680,
	
	"effects": [
		{
			"type": "trail",
			"trail_type": "lightnings",
			"color": [1,0,0],
			"use_suit_trails": true,
			"conditions": [
				{
					"type": "ability_enabled",
					"ability": "toggle_power"
				},
				{
					"type": "moving"
				}
			]
		},
		{
			"type": "name_change",
			"name": {
				"text": "🎵Yondu🎵"
			},
			"conditions": [
				{
					"type": "ability_enabled",
					"ability": "toggle_power"
				}
			]
		}
	],
	
	"abilities": [
		{
			"ability": "lucraftcore:toggle_power",
			"title": {"text":"Activate Yondu Powers"},
			"abilities": [],
			"icon": {
				"type": "texture",
				"texture": "yondu:textures/icons/yondu_icon.png"
			}
		},
		{
			"ability": "lucraftcore:flight",
			"speed": 0.6,
			"sprint_speed": 1.5,
			"rotate_arms": true,
			"required_ability": "toggle_power",
			"title": {"text":"Yaka Arrow Flight"}
		},
		{
			"ability": "lucraftcore:sprint",
			"amount": 4,
			"operation": 0,
			"uuid": "b2930a55-fa9d-4124-bb58-2ba3169d1495",
			"required_ability": "toggle_power"
		},
		{
			"ability": "lucraftcore:healing",
			"frequency": 10,
			"amount": 1,
			"required_ability": "toggle_power"
		},
		{
			"ability": "lucraftcore:strength",
			"amount": 3,
			"operation": 0,
			"uuid": "ff38d1b5-fd0c-4063-ae71-0838291e118e",
			"required_ability": "toggle_power"
		},
		{
			"ability": "lucraftcore:punch",
			"amount": 4,
			"operation": 0,
			"uuid": "ff38d1b5-fd0c-4063-ae71-0838291e118e",
			"required_ability": "toggle_power",
			"required_level": 2
		},
		{
			"ability": "lucraftcore:fall_resistance",
			"amount": 8,
			"operation": 0,
			"uuid": "ff38d1b5-fd0c-4063-ae71-0838291e118e",
			"required_ability": "toggle_power"
		},
		{
			"ability": "lucraftcore:jump_boost",
			"amount": 3,
			"operation": 0,
			"uuid": "ff38d1b5-fd0c-4063-ae71-0838291e118e",
			"required_ability": "toggle_power"
		},
		{
			"ability": "lucraftcore:step_assist",
			"amount": 2,
			"operation": 0,
			"uuid": "b2930a55-fa9d-4124-bb58-2ba3169d1495",
			"required_ability": "toggle_power"
		},
		{
			"ability": "lucraftcore:health",
			"amount": 10,
			"operation": 0,
			"uuid": "b2930a55-fa9d-4124-bb58-2ba3169d1495",
			"required_ability": "toggle_power"
		},
		{
			"ability": "lucraftcore:resistance",
			"amount": 5,
			"operation": 0,
			"uuid": "b2930a55-fa9d-4124-bb58-2ba3169d1495",
			"required_ability": "toggle_power"
		},
		{
			"ability": "lucraftcore:tough_lungs",
			"required_ability": "toggle_power"
		},
		{
			"ability": "lucraftcore:water_breathing",
			"required_ability": "toggle_power"
		},
		{
			"ability": "lucraftcore:fire_resistance",
			"required_ability": "toggle_power"
		}
	]
}